bucketratelimiter/__init__.py
bucketratelimiter/version.py
bucketratelimiter/bucket_rate_limiters/__init__.py
bucketratelimiter/bucket_rate_limiters/asyncio_bucket.py
bucketratelimiter/bucket_rate_limiters/bucket_abc.py
bucketratelimiter/bucket_rate_limiters/mthreaded_bucket.py
bucketratelimiter-1.0.0.dist-info/LICENSE
bucketratelimiter-1.0.0.dist-info/METADATA
bucketratelimiter-1.0.0.dist-info/WHEEL
bucketratelimiter-1.0.0.dist-info/top_level.txt
bucketratelimiter-1.0.0.dist-info/RECORD
