Metadata-Version: 2.1
Name: bucketratelimiter
Version: 1.0.0
Summary: Collection of BucketRateLimiters. Allows to limit number of ops to the certain number.
Author: Artyom Viktorovich Kozyrev
Author-email: kozirev8@gmail.com
License: GNU GENERAL PUBLIC LICENSE
Project-URL: Documentation, https://github.com/ArtyomKozyrev8/BucketRateLimiter/
Project-URL: Source, https://github.com/ArtyomKozyrev8/BucketRateLimiter/
Platform: all
Classifier: License :: OSI Approved :: GNU Affero General Public License v3
Classifier: Topic :: Internet
Classifier: Topic :: Software Development
Classifier: Topic :: Software Development :: Libraries
Classifier: Intended Audience :: Developers
Classifier: Natural Language :: English
Classifier: Operating System :: MacOS
Classifier: Operating System :: POSIX
Classifier: Operating System :: Microsoft
Classifier: Programming Language :: Python
Classifier: Programming Language :: Python :: 3
Classifier: Programming Language :: Python :: 3.6
Classifier: Programming Language :: Python :: 3.7
Classifier: Programming Language :: Python :: 3.8
Classifier: Programming Language :: Python :: 3.9
Classifier: Programming Language :: Python :: 3.10
Classifier: Programming Language :: Python :: Implementation :: CPython
Requires-Python: >=3.6, <4
License-File: LICENSE
Provides-Extra: develop
Requires-Dist: mypy ; extra == 'develop'
Requires-Dist: pytest-cov ; extra == 'develop'
Requires-Dist: pytest-asyncio ; extra == 'develop'
